disk_formator/__about__.py
disk_formator/__init__.py
disk_formator-1.0.0.dist-info/METADATA
disk_formator-1.0.0.dist-info/WHEEL
disk_formator-1.0.0.dist-info/licenses/LICENSE.txt
disk_formator-1.0.0.dist-info/RECORD
