Metadata-Version: 2.1
Name: disk-formator
Version: 1.0.0
Summary: It's a little program in Python to format disks.
Project-URL: Documentation, https://github.com/Useless-Projects/disk-formator#readme
Project-URL: Issues, https://github.com/Useless-Projects/disk-formator/issues
Project-URL: Source, https://github.com/Useless-Projects/disk-formator
Author-email: Thibault Savenkoff <thibault.savenkoff@outlook.fr>
License-Expression: MIT
License-File: LICENSE.txt
Classifier: Development Status :: 5 - Production/Stable
Classifier: Environment :: Console
Classifier: Framework :: Hatch
Classifier: Intended Audience :: System Administrators
Classifier: License :: OSI Approved :: MIT License
Classifier: Natural Language :: English
Classifier: Operating System :: MacOS
Classifier: Operating System :: Microsoft :: Windows
Classifier: Operating System :: POSIX
Classifier: Programming Language :: Python
Classifier: Programming Language :: Python :: 3 :: Only
Classifier: Programming Language :: Python :: 3.7
Classifier: Programming Language :: Python :: 3.8
Classifier: Programming Language :: Python :: 3.9
Classifier: Programming Language :: Python :: 3.10
Classifier: Programming Language :: Python :: 3.11
Classifier: Programming Language :: Python :: 3.12
Classifier: Programming Language :: Python :: Implementation :: CPython
Classifier: Programming Language :: Python :: Implementation :: PyPy
Classifier: Topic :: Security
Classifier: Topic :: System
Requires-Python: >=3.7
Requires-Dist: psutil
